perceptron_package/__init__.py
perceptron_package/all_utils_class.py
perceptron_package/perceptron_class.py
Perceptron_RabiaWadhwa-0.0.2.dist-info/LICENSE
Perceptron_RabiaWadhwa-0.0.2.dist-info/METADATA
Perceptron_RabiaWadhwa-0.0.2.dist-info/WHEEL
Perceptron_RabiaWadhwa-0.0.2.dist-info/top_level.txt
Perceptron_RabiaWadhwa-0.0.2.dist-info/RECORD
